aiogram3_triggers/__init__.py
aiogram3_triggers/triggers.py
aiogram3_triggers-0.0.3.dist-info/LICENSE
aiogram3_triggers-0.0.3.dist-info/METADATA
aiogram3_triggers-0.0.3.dist-info/WHEEL
aiogram3_triggers-0.0.3.dist-info/top_level.txt
aiogram3_triggers-0.0.3.dist-info/RECORD
