Metadata-Version: 2.1
Name: aiogram3-triggers
Version: 0.0.3
Summary: Aiogram3 Triggers
Home-page: https://github.com/zcxw-code/aiogram3-triggers
Author: Zcxw
Author-email: zcxw.code@hotmail.com
Classifier: Programming Language :: Python :: 3
Classifier: Operating System :: OS Independent
Requires-Python: >=3.8
License-File: LICENSE
